ctkdateentry/__init__.py
ctkdateentry/ctkdateentry.py
CTkDateEntry-0.1.2.dist-info/LICENSE
CTkDateEntry-0.1.2.dist-info/METADATA
CTkDateEntry-0.1.2.dist-info/WHEEL
CTkDateEntry-0.1.2.dist-info/top_level.txt
CTkDateEntry-0.1.2.dist-info/RECORD
